{
  "101": {
    "desc": "阳光、海浪与绵长沙滩交织而成的天然游乐场，是夏日最惬意的踏浪之地。",
    "icon": "huangjinhaian",
    "id": 101,
    "lua": "",
    "name": "黄金海岸",
    "posion": [
      653,
      -269,
      0
    ],
    "type": 1
  },
  "102": {
    "desc": "海上往来的枢纽，各色船只在此停靠，送来各色的奢华珍宝。",
    "icon": "gangkou",
    "id": 102,
    "lua": "",
    "name": "港口",
    "posion": [
      1019,
      168,
      0
    ],
    "type": 1
  },
  "103": {
    "desc": "由“船锚”造型串联而起的海上空间，漫步其上，仿佛行走于潮汐之间。",
    "icon": "rengongqundao",
    "id": 103,
    "lua": "",
    "name": "人工群岛",
    "posion": [
      1005,
      -78,
      0
    ],
    "type": 1
  },
  "104": {
    "desc": "以独树一帜的外观引人注目的高端酒店，其屋顶泳池深受游客喜爱。",
    "icon": "qiongdingjiudian",
    "id": 104,
    "lua": "",
    "name": "穹顶酒店",
    "posion": [
      -341,
      -20,
      0
    ],
    "type": 1
  },
  "105": {
    "desc": "象征着品味和格调的城市地标建筑，也是位于浮金湾核心地段的顶级商业中心。",
    "icon": "fujindasha",
    "id": 105,
    "lua": "",
    "name": "浮金大厦",
    "posion": [
      -40,
      62,
      0
    ],
    "type": 1
  },
  "106": {
    "desc": "专为盛大活动打造的奢华空间，弥漫着华美与梦幻的气息。",
    "icon": "tianfangyanhuiting",
    "id": 106,
    "lua": "",
    "name": "天方宴会厅",
    "posion": [
      155,
      35,
      0
    ],
    "type": 1
  },
  "107": {
    "desc": "紧邻海岸的居停之所，是放松身心、享受假日时光的理想选择。",
    "icon": "haifengjiudian",
    "id": 107,
    "lua": "",
    "name": "海风酒店",
    "posion": [
      172,
      -331,
      0
    ],
    "type": 1
  },
  "108": {
    "desc": "将奇想和现实完美融合的科技馆，置身其中便可穿越虚实边界，开启奇妙的探索之旅。",
    "icon": "kejiguan",
    "id": 108,
    "lua": "",
    "name": "科技馆",
    "posion": [
      -252,
      -242,
      0
    ],
    "type": 1
  },
  "109": {
    "desc": "欢笑与尖叫交织的梦幻王国，踏入此地便可尽情享受纯粹的快乐。",
    "icon": "youleyuan",
    "id": 109,
    "lua": "",
    "name": "游乐园",
    "posion": [
      -546,
      -224,
      0
    ],
    "type": 1
  },
  "110": {
    "desc": "空气中弥漫着馥郁香气，琳琅满目的摊位间汇集了来自世界各地的香料。",
    "icon": "xiangliaoshichang",
    "id": 110,
    "lua": "",
    "name": "香料市场",
    "posion": [
      -700,
      476,
      0
    ],
    "type": 1
  },
  "111": {
    "desc": "店铺林立的蜿蜒街巷，从精美的手工艺品到地道的小吃饮品应有尽有。",
    "icon": "fengqingjie",
    "id": 111,
    "lua": "",
    "name": "风情街",
    "posion": [
      -478,
      408,
      0
    ],
    "type": 1
  },
  "112": {
    "desc": "一座巨大的海洋场馆，步入其中可与众多海洋生物们来一场近距离邂逅。",
    "icon": "shuizuguan",
    "id": 112,
    "lua": "",
    "name": "水族馆",
    "posion": [
      -680,
      254,
      0
    ],
    "type": 1
  },
  "113": {
    "desc": "一片开阔的黄沙，是体验沙漠旅行，举办活动露营的绝佳之地。",
    "icon": "qiansha",
    "id": 113,
    "lua": "",
    "name": "浅沙",
    "posion": [
      140,
      531,
      0
    ],
    "type": 1
  },
  "114": {
    "desc": "对称分割的花田簇拥着中央亭台，芬芳四溢中构成一幅生机勃勃的画卷。",
    "icon": "qijihuayuan",
    "id": 114,
    "lua": "",
    "name": "奇迹花园",
    "posion": [
      -164,
      401,
      0
    ],
    "type": 1
  },
  "115": {
    "desc": "镶嵌于沙漠和繁华都市之间的静谧水域，每一寸绿化都是财富的象征。",
    "icon": "rengonghu",
    "id": 115,
    "lua": "",
    "name": "人工湖",
    "posion": [
      472,
      517,
      0
    ],
    "type": 1
  },
  "201": {
    "desc": "阁下，该醒咯~",
    "icon": "icon_1",
    "id": 201,
    "lua": "SHEHUAXIANGMENGFUJINWAN1",
    "name": "阁下，该醒咯~",
    "posion": [
      327,
      198,
      0
    ],
    "type": 2
  },
  "202": {
    "desc": "昙花一现的宝石",
    "icon": "icon_1",
    "id": 202,
    "lua": "SHEHUAXIANGMENGFUJINWAN19",
    "name": "昙花一现的宝石",
    "posion": [
      -341,
      -20,
      0
    ],
    "type": 2
  },
  "203": {
    "desc": "海鸥的踪迹",
    "icon": "icon_1",
    "id": 203,
    "lua": "SHEHUAXIANGMENGFUJINWAN20",
    "name": "海鸥的踪迹",
    "posion": [
      1019,
      168,
      0
    ],
    "type": 2
  },
  "204": {
    "desc": "屋顶上的“海盗”",
    "icon": "icon_1",
    "id": 204,
    "lua": "SHEHUAXIANGMENGFUJINWAN21",
    "name": "屋顶上的“海盗”",
    "posion": [
      172,
      -331,
      0
    ],
    "type": 2
  },
  "205": {
    "desc": "神·灯·小·姐",
    "icon": "icon_1",
    "id": 205,
    "lua": "SHEHUAXIANGMENGFUJINWAN22",
    "name": "神·灯·小·姐",
    "posion": [
      -478,
      408,
      0
    ],
    "type": 2
  },
  "206": {
    "desc": "“魔法”花园的晚宴",
    "icon": "icon_1",
    "id": 206,
    "lua": "SHEHUAXIANGMENGFUJINWAN23",
    "name": "“魔法”花园的晚宴",
    "posion": [
      140,
      531,
      0
    ],
    "type": 2
  },
  "207": {
    "desc": "奇迹之光",
    "icon": "icon_1",
    "id": 207,
    "lua": "SHEHUAXIANGMENGFUJINWAN24",
    "name": "奇迹之光",
    "posion": [
      -164,
      401,
      0
    ],
    "type": 2
  },
  "208": {
    "desc": "为你献上的礼物",
    "icon": "icon_1",
    "id": 208,
    "lua": "SHEHUAXIANGMENGFUJINWAN2",
    "name": "为你献上的礼物",
    "posion": [
      653,
      -269,
      0
    ],
    "type": 2
  },
  "301": {
    "desc": "",
    "icon": "gangkou",
    "id": 301,
    "lua": "SHEHUAXIANGMENGFUJINWAN13",
    "name": "意外被困的捉迷藏游戏",
    "posion": [
      1019,
      168,
      0
    ],
    "type": 3
  },
  "302": {
    "desc": "",
    "icon": "rengongqundao",
    "id": 302,
    "lua": "SHEHUAXIANGMENGFUJINWAN14",
    "name": "沙滩雕塑大赛进行中！",
    "posion": [
      1005,
      -78,
      0
    ],
    "type": 3
  },
  "303": {
    "desc": "",
    "icon": "youleyuan",
    "id": 303,
    "lua": "SHEHUAXIANGMENGFUJINWAN15",
    "name": "此刻，与谁共赴？",
    "posion": [
      -546,
      -224,
      0
    ],
    "type": 3
  },
  "304": {
    "desc": "",
    "icon": "xiangliaoshichang",
    "id": 304,
    "lua": "SHEHUAXIANGMENGFUJINWAN16",
    "name": "特别拍摄计划",
    "posion": [
      -700,
      476,
      0
    ],
    "type": 3
  },
  "305": {
    "desc": "",
    "icon": "fengqingjie",
    "id": 305,
    "lua": "SHEHUAXIANGMENGFUJINWAN17",
    "name": "氤氲之中",
    "posion": [
      -478,
      408,
      0
    ],
    "type": 3
  },
  "306": {
    "desc": "",
    "icon": "qiansha",
    "id": 306,
    "lua": "SHEHUAXIANGMENGFUJINWAN18",
    "name": "沙洲越野赛！",
    "posion": [
      140,
      531,
      0
    ],
    "type": 3
  },
  "401": {
    "desc": "1",
    "icon": "yanusi",
    "id": 401,
    "lua": "SHEHUAXIANGMENGFUJINWAN3",
    "name": "云端的水光",
    "posion": [
      960,
      540,
      0
    ],
    "type": 4
  },
  "402": {
    "desc": "2",
    "icon": "mojiaduoer",
    "id": 402,
    "lua": "SHEHUAXIANGMENGFUJINWAN4",
    "name": "直至心跳相融",
    "posion": [
      960,
      540,
      0
    ],
    "type": 4
  },
  "403": {
    "desc": "3",
    "icon": "luyijiushi",
    "id": 403,
    "lua": "SHEHUAXIANGMENGFUJINWAN5",
    "name": "蜜渍余甘",
    "posion": [
      960,
      540,
      0
    ],
    "type": 4
  },
  "404": {
    "desc": "4",
    "icon": "u2501",
    "id": 404,
    "lua": "SHEHUAXIANGMENGFUJINWAN6",
    "name": "水幕画心",
    "posion": [
      960,
      540,
      0
    ],
    "type": 4
  },
  "405": {
    "desc": "5",
    "icon": "aimudeng",
    "id": 405,
    "lua": "SHEHUAXIANGMENGFUJINWAN7",
    "name": "水畔的夕暮私语",
    "posion": [
      960,
      540,
      0
    ],
    "type": 4
  },
  "406": {
    "desc": "6",
    "icon": "gezi",
    "id": 406,
    "lua": "SHEHUAXIANGMENGFUJINWAN8",
    "name": "赤红之月的幻想",
    "posion": [
      960,
      540,
      0
    ],
    "type": 4
  },
  "407": {
    "desc": "7",
    "icon": "tianchengcv",
    "id": 407,
    "lua": "SHEHUAXIANGMENGFUJINWAN9",
    "name": "碧波绮尾",
    "posion": [
      960,
      540,
      0
    ],
    "type": 4
  },
  "408": {
    "desc": "8",
    "icon": "moliciqinwang",
    "id": 408,
    "lua": "SHEHUAXIANGMENGFUJINWAN10",
    "name": "神灯小姐的愿望游戏",
    "posion": [
      960,
      540,
      0
    ],
    "type": 4
  },
  "409": {
    "desc": "9",
    "icon": "aogusite",
    "id": 409,
    "lua": "SHEHUAXIANGMENGFUJINWAN11",
    "name": "与“魔女”的星夜之约",
    "posion": [
      960,
      540,
      0
    ],
    "type": 4
  },
  "410": {
    "desc": "10",
    "icon": "z15",
    "id": 410,
    "lua": "SHEHUAXIANGMENGFUJINWAN12",
    "name": "水上的心跳“意外”",
    "posion": [
      960,
      540,
      0
    ],
    "type": 4
  },
  "__name": "activity_mall_story",
  "all": [
    101,
    102,
    103,
    104,
    105,
    106,
    107,
    108,
    109,
    110,
    111,
    112,
    113,
    114,
    115,
    201,
    202,
    203,
    204,
    205,
    206,
    207,
    208,
    301,
    302,
    303,
    304,
    305,
    306,
    401,
    402,
    403,
    404,
    405,
    406,
    407,
    408,
    409,
    410
  ]
}